jinjacraft/__init__.py
jinjacraft/exceptions.py
jinjacraft/main.py
jinjacraft/model_generator.py
jinjacraft/renderer.py
jinjacraft/validator.py
jinjacraft-1.5.2.dist-info/METADATA
jinjacraft-1.5.2.dist-info/WHEEL
jinjacraft-1.5.2.dist-info/entry_points.txt
jinjacraft-1.5.2.dist-info/licenses/LICENCE
jinjacraft-1.5.2.dist-info/RECORD
