Metadata-Version: 2.4
Name: jinjacraft
Version: 1.5.2
Summary: Python command-line tool to generates text files based on Jinja2 template and YAML data file.
License: MIT
License-File: LICENCE
Keywords: jinja2,yaml,template,command-line
Author: Steve De Jongh
Author-email: dejongh.st@gmail.com
Requires-Python: >=3.9
Classifier: Development Status :: 5 - Production/Stable
Classifier: Environment :: Console
Classifier: License :: OSI Approved :: MIT License
Classifier: Operating System :: OS Independent
Classifier: Programming Language :: Python :: 3
Classifier: Programming Language :: Python :: 3.9
Classifier: Programming Language :: Python :: 3.10
Classifier: Programming Language :: Python :: 3.11
Classifier: Programming Language :: Python :: 3.12
Classifier: Programming Language :: Python :: 3.13
Classifier: Programming Language :: Python :: 3.14
Classifier: Topic :: Text Processing :: General
Classifier: Topic :: Utilities
Requires-Dist: jinja2 (>=3.1.2,<4.0.0)
Requires-Dist: pytest (>=7.4.0,<8.0.0)
Requires-Dist: pyyaml (>=6.0.1,<7.0.0)
Project-URL: Bug Tracker, https://github.com/sdejongh/jinjacraft/issues
Project-URL: Repository, https://github.com/sdejongh/jinjacraft
